fullnamesplitter/__init__.py
fullnamesplitter/names.db
spanishfullnamesplitter-0.1.5.dist-info/METADATA
spanishfullnamesplitter-0.1.5.dist-info/WHEEL
spanishfullnamesplitter-0.1.5.dist-info/RECORD
