Metadata-Version: 2.4
Name: spanishfullnamesplitter
Version: 0.1.5
Summary: Extract name and surnames of spanish people from string
Author-email: Fran Lendinez <flendinez@grupovisalia.com>
Requires-Python: >=3.5
Requires-Dist: unidecode>=1.3.8
